yosafe_packages/yosafe_subpackage_3/__init__.py
yosafe_all_packages-0.1.0.dist-info/METADATA
yosafe_all_packages-0.1.0.dist-info/WHEEL
yosafe_all_packages-0.1.0.dist-info/RECORD
